name_that_hash/HashTypeObj.py
name_that_hash/__init__.py
name_that_hash/__main__.py
name_that_hash/check_hashes.py
name_that_hash/hash_info.py
name_that_hash/hash_namer.py
name_that_hash/hashes.py
name_that_hash/prettifier.py
name_that_hash/runner.py
name_that_hash-1.11.0.dist-info/entry_points.txt
name_that_hash-1.11.0.dist-info/LICENSE
name_that_hash-1.11.0.dist-info/WHEEL
name_that_hash-1.11.0.dist-info/METADATA
name_that_hash-1.11.0.dist-info/RECORD
