Metadata-Version: 2.1
Name: name-that-hash
Version: 1.11.0
Summary: The Modern Hash Identification System
License: GPL-3.0-or-later
Author: autumn
Author-email: autumn@skerritt.blog
Requires-Python: >=3.6.2,<4.0.0
Classifier: License :: OSI Approved :: GNU General Public License v3 or later (GPLv3+)
Classifier: Programming Language :: Python :: 3
Classifier: Programming Language :: Python :: 3.7
Classifier: Programming Language :: Python :: 3.8
Classifier: Programming Language :: Python :: 3.9
Classifier: Programming Language :: Python :: 3.10
Classifier: Programming Language :: Python :: 3.11
Requires-Dist: click (>=7.1.2)
Requires-Dist: rich (>=11.0.0)
